{
  "id": "ic_timer_timer04_tssop8",
  "name": "Astra 558 Precision Timer (TSSOP-8)",
  "component_type": "ic",
  "description": "Template for Astra 558 Precision Timer packaged as TSSOP-8",
  "width": 160,
  "height": 220,
  "pins": [
    {
      "id": "GND",
      "label": "GND",
      "pin_type": "ground",
      "position": [
        0,
        0
      ]
    },
    {
      "id": "TRIG",
      "label": "TRIG",
      "pin_type": "analog",
      "position": [
        0,
        28
      ]
    },
    {
      "id": "OUT",
      "label": "OUT",
      "pin_type": "digital",
      "position": [
        0,
        56
      ]
    },
    {
      "id": "RESET",
      "label": "RESET",
      "pin_type": "digital",
      "position": [
        0,
        84
      ]
    },
    {
      "id": "CTRL",
      "label": "CTRL",
      "pin_type": "analog",
      "position": [
        160,
        84
      ]
    },
    {
      "id": "THRES",
      "label": "TH",
      "pin_type": "analog",
      "position": [
        160,
        56
      ]
    },
    {
      "id": "DISCH",
      "label": "DIS",
      "pin_type": "digital",
      "position": [
        160,
        28
      ]
    },
    {
      "id": "VCC",
      "label": "VCC",
      "pin_type": "power",
      "position": [
        160,
        0
      ]
    }
  ],
  "metadata": {
    "manufacturer": "Nova Circuits",
    "part_number": "Astra-TIMER04-TSSOP8",
    "package": "TSSOP-8",
    "operating_limits": {
      "supply_voltage": "3V to 18V",
      "temperature": "-55\u00b0C to 125\u00b0C"
    },
    "datasheet_url": "https://example.com/datasheets/timer04.pdf",
    "channels": 1
  }
}
